jsonlogic/__init__.py
jsonlogic/_compat.py
jsonlogic/core.py
jsonlogic/py.typed
jsonlogic/registry.py
jsonlogic/resolving.py
jsonlogic/typing.py
jsonlogic/utils.py
jsonlogic/evaluation/__init__.py
jsonlogic/evaluation/evaluation_context.py
jsonlogic/evaluation/evaluation_settings.py
jsonlogic/evaluation/utils.py
jsonlogic/json_schema/__init__.py
jsonlogic/json_schema/types.py
jsonlogic/operators/__init__.py
jsonlogic/operators/operators.py
jsonlogic/typechecking/__init__.py
jsonlogic/typechecking/diagnostics.py
jsonlogic/typechecking/typecheck_context.py
jsonlogic/typechecking/typecheck_settings.py
jsonlogic/typechecking/utils.py
python_jsonlogic-0.1.0.dist-info/LICENSE
python_jsonlogic-0.1.0.dist-info/METADATA
python_jsonlogic-0.1.0.dist-info/WHEEL
python_jsonlogic-0.1.0.dist-info/top_level.txt
python_jsonlogic-0.1.0.dist-info/RECORD
