Metadata-Version: 2.1
Name: python-jsonlogic
Version: 0.1.0
Summary: An extensible and sane implementation of JsonLogic
Author-email: Victorien <contact@vctrn.dev>
License: MIT License
Classifier: Development Status :: 4 - Beta
Classifier: Operating System :: OS Independent
Classifier: Programming Language :: Python :: 3
Classifier: Programming Language :: Python :: 3 :: Only
Classifier: Programming Language :: Python :: 3.8
Classifier: Programming Language :: Python :: 3.9
Classifier: Programming Language :: Python :: 3.10
Classifier: Programming Language :: Python :: 3.11
Classifier: Programming Language :: Python :: 3.12
Classifier: Typing :: Typed
Classifier: License :: OSI Approved :: MIT License
Classifier: Intended Audience :: Developers
Classifier: Topic :: Software Development :: Libraries :: Python Modules
Requires-Python: >=3.8
License-File: LICENSE
Requires-Dist: typing-extensions >=4.10.0 ; python_version < "3.13"
